fateslist/__init__.py
fateslist/classes.py
fateslist/config.py
fateslist/http.py
fateslist/main.py
fateslist/system.py
fateslist/utils.py
fateslist/ws.py
fateslist-1.0.0.dist-info/LICENSE
fateslist-1.0.0.dist-info/METADATA
fateslist-1.0.0.dist-info/WHEEL
fateslist-1.0.0.dist-info/top_level.txt
fateslist-1.0.0.dist-info/RECORD
