Metadata-Version: 2.1
Name: fateslist
Version: 1.0.0
Summary: fateslist is a API Wrapper for Fates List (https://fateslist.xyz)
Home-page: https://github.com/Fates-List/fateslist.py
Author: Rootspring
Author-email: tor_needletail@outlook.com
License: MIT
Project-URL: Bug Tracker, https://github.com/Fates-List/fateslist.py/issues
Platform: UNKNOWN
Classifier: Programming Language :: Python :: 3
Classifier: License :: OSI Approved :: MIT License
Classifier: Operating System :: OS Independent
License-File: LICENSE
Requires-Dist: aiohttp
Requires-Dist: loguru
Requires-Dist: discord
